{"top":[{"id":"ZZ","name":"Unknown","domains":119317,"share":0.398658},{"id":"US","name":"United States of America","domains":75736,"share":0.253046},{"id":"IS","name":"Iceland","domains":19850,"share":0.0663221},{"id":"CN","name":"China","domains":15439,"share":0.0515842},{"id":"CA","name":"Canada","domains":12079,"share":0.0403579},{"id":"NL","name":"Netherlands","domains":7939,"share":0.0265255},{"id":"XX","name":"Hidden","domains":4952,"share":0.0165454},{"id":"GB","name":"United Kingdom of Great Britain and Northern Ireland","domains":3723,"share":0.0124391},{"id":"JP","name":"Japan","domains":3693,"share":0.0123389},{"id":"IN","name":"India","domains":3248,"share":0.0108521},{"id":"FR","name":"France","domains":2474,"share":0.00826604},{"id":"BR","name":"Brazil","domains":2464,"share":0.00823263},{"id":"RU","name":"Russian Federation","domains":2115,"share":0.00706656},{"id":"DE","name":"Germany","domains":1765,"share":0.00589715},{"id":"TR","name":"Turkey","domains":1636,"share":0.00546614},{"id":"IT","name":"Italy","domains":1623,"share":0.00542271},{"id":"ID","name":"Indonesia","domains":1213,"share":0.00405283},{"id":"VN","name":"Viet Nam","domains":1200,"share":0.00400939},{"id":"GA","name":"Gabon","domains":1082,"share":0.00361514},{"id":"ES","name":"Spain","domains":984,"share":0.0032877},{"id":"ZA","name":"South Africa","domains":875,"share":0.00292352},{"id":"MY","name":"Malaysia","domains":825,"share":0.00275646},{"id":"SG","name":"Singapore","domains":823,"share":0.00274978},{"id":"AU","name":"Australia","domains":716,"share":0.00239227},{"id":"MX","name":"Mexico","domains":701,"share":0.00234215},{"id":"PA","name":"Panama","domains":683,"share":0.00228201},{"id":"UA","name":"Ukraine","domains":654,"share":0.00218512},{"id":"NG","name":"Nigeria","domains":548,"share":0.00183096},{"id":"PL","name":"Poland","domains":540,"share":0.00180423},{"id":"HK","name":"Hong Kong","domains":526,"share":0.00175745},{"id":"AR","name":"Argentina","domains":523,"share":0.00174743},{"id":"CZ","name":"Czechia","domains":520,"share":0.0017374},{"id":"KR","name":"Korea, Republic of","domains":464,"share":0.0015503},{"id":"TW","name":"Taiwan, Province of China","domains":403,"share":0.00134649},{"id":"HU","name":"Hungary","domains":370,"share":0.00123623},{"id":"CO","name":"Colombia","domains":318,"share":0.00106249},{"id":"CH","name":"Switzerland","domains":294,"share":0.000982301},{"id":"PK","name":"Pakistan","domains":274,"share":0.000915478},{"id":"DK","name":"Denmark","domains":270,"share":0.000902113},{"id":"AT","name":"Austria","domains":249,"share":0.000831949},{"id":"IL","name":"Israel","domains":231,"share":0.000771808},{"id":"KZ","name":"Kazakhstan","domains":231,"share":0.000771808},{"id":"BS","name":"Bahamas","domains":218,"share":0.000728373},{"id":"PH","name":"Philippines","domains":205,"share":0.000684938},{"id":"NZ","name":"New Zealand","domains":202,"share":0.000674914},{"id":"TH","name":"Thailand","domains":198,"share":0.00066155},{"id":"AE","name":"United Arab Emirates","domains":193,"share":0.000644844},{"id":"BD","name":"Bangladesh","domains":188,"share":0.000628138},{"id":"SK","name":"Slovakia","domains":187,"share":0.000624797},{"id":"PT","name":"Portugal","domains":185,"share":0.000618115},{"id":"BE","name":"Belgium","domains":180,"share":0.000601409},{"id":"RO","name":"Romania","domains":178,"share":0.000594726},{"id":"SE","name":"Sweden","domains":177,"share":0.000591385},{"id":"KE","name":"Kenya","domains":154,"share":0.000514539},{"id":"MA","name":"Morocco","domains":152,"share":0.000507856},{"id":"BG","name":"Bulgaria","domains":151,"share":0.000504515},{"id":"NO","name":"Norway","domains":149,"share":0.000497833},{"id":"SA","name":"Saudi Arabia","domains":130,"share":0.000434351},{"id":"MT","name":"Malta","domains":125,"share":0.000417645},{"id":"KN","name":"Saint Kitts and Nevis","domains":121,"share":0.00040428},{"id":"FI","name":"Finland","domains":117,"share":0.000390916},{"id":"EG","name":"Egypt","domains":105,"share":0.000350822},{"id":"GR","name":"Greece","domains":103,"share":0.000344139},{"id":"CY","name":"Cyprus","domains":92,"share":0.000307386},{"id":"IR","name":"Iran (Islamic Republic of)","domains":88,"share":0.000294022},{"id":"EE","name":"Estonia","domains":86,"share":0.00028734},{"id":"PE","name":"Peru","domains":78,"share":0.00026061},{"id":"CL","name":"Chile","domains":75,"share":0.000250587},{"id":"UZ","name":"Uzbekistan","domains":75,"share":0.000250587},{"id":"GH","name":"Ghana","domains":70,"share":0.000233881},{"id":"KY","name":"Cayman Islands","domains":70,"share":0.000233881},{"id":"RS","name":"Serbia","domains":66,"share":0.000220516},{"id":"IE","name":"Ireland","domains":64,"share":0.000213834},{"id":"BY","name":"Belarus","domains":54,"share":0.000180422},{"id":"HR","name":"Croatia","domains":50,"share":0.000167058},{"id":"DZ","name":"Algeria","domains":48,"share":0.000160375},{"id":"EC","name":"Ecuador","domains":44,"share":0.000147011},{"id":"TN","name":"Tunisia","domains":44,"share":0.000147011},{"id":"NP","name":"Nepal","domains":43,"share":0.00014367},{"id":"TJ","name":"Tajikistan","domains":41,"share":0.000136987},{"id":"CR","name":"Costa Rica","domains":40,"share":0.000133646},{"id":"LU","name":"Luxembourg","domains":39,"share":0.000130305},{"id":"AM","name":"Armenia","domains":37,"share":0.000123623},{"id":"KH","name":"Cambodia","domains":36,"share":0.000120281},{"id":"CM","name":"Cameroon","domains":34,"share":0.000113599},{"id":"VE","name":"Venezuela (Bolivarian Republic of)","domains":34,"share":0.000113599},{"id":"CI","name":"C\u00f4te d'Ivoire","domains":32,"share":0.000106917},{"id":"ER","name":"Eritrea","domains":31,"share":0.000103576},{"id":"SC","name":"Seychelles","domains":31,"share":0.000103576},{"id":"SI","name":"Slovenia","domains":31,"share":0.000103576},{"id":"AF","name":"Afghanistan","domains":28,"share":9.3552e-5},{"id":"LT","name":"Lithuania","domains":28,"share":9.3552e-5},{"id":"UG","name":"Uganda","domains":24,"share":8.0187e-5},{"id":"BJ","name":"Benin","domains":23,"share":7.6846e-5},{"id":"BO","name":"Bolivia (Plurinational State of)","domains":22,"share":7.3505e-5},{"id":"LV","name":"Latvia","domains":22,"share":7.3505e-5},{"id":"PY","name":"Paraguay","domains":22,"share":7.3505e-5},{"id":"CD","name":"Congo, Democratic Republic of the","domains":21,"share":7.0164e-5},{"id":"DO","name":"Dominican Republic","domains":21,"share":7.0164e-5},{"id":"JO","name":"Jordan","domains":21,"share":7.0164e-5},{"id":"LK","name":"Sri Lanka","domains":21,"share":7.0164e-5},{"id":"MM","name":"Myanmar","domains":21,"share":7.0164e-5},{"id":"IQ","name":"Iraq","domains":20,"share":6.6823e-5},{"id":"PR","name":"Puerto Rico","domains":20,"share":6.6823e-5},{"id":"GE","name":"Georgia","domains":18,"share":6.014e-5},{"id":"GG","name":"Guernsey","domains":18,"share":6.014e-5},{"id":"TC","name":"Turks and Caicos Islands","domains":17,"share":5.6799e-5},{"id":"OM","name":"Oman","domains":15,"share":5.0117e-5},{"id":"UY","name":"Uruguay","domains":15,"share":5.0117e-5},{"id":"AZ","name":"Azerbaijan","domains":14,"share":4.6776e-5},{"id":"HN","name":"Honduras","domains":14,"share":4.6776e-5},{"id":"MN","name":"Mongolia","domains":14,"share":4.6776e-5},{"id":"ZM","name":"Zambia","domains":14,"share":4.6776e-5},{"id":"AW","name":"Aruba","domains":13,"share":4.3435e-5},{"id":"GT","name":"Guatemala","domains":13,"share":4.3435e-5},{"id":"KW","name":"Kuwait","domains":13,"share":4.3435e-5},{"id":"SN","name":"Senegal","domains":13,"share":4.3435e-5},{"id":"TZ","name":"Tanzania, United Republic of","domains":13,"share":4.3435e-5},{"id":"YE","name":"Yemen","domains":13,"share":4.3435e-5},{"id":"LB","name":"Lebanon","domains":12,"share":4.0093e-5},{"id":"AL","name":"Albania","domains":11,"share":3.6752e-5},{"id":"MK","name":"North Macedonia","domains":11,"share":3.6752e-5},{"id":"AO","name":"Angola","domains":10,"share":3.3411e-5},{"id":"MZ","name":"Mozambique","domains":10,"share":3.3411e-5},{"id":"NA","name":"Namibia","domains":10,"share":3.3411e-5},{"id":"ZW","name":"Zimbabwe","domains":10,"share":3.3411e-5},{"id":"LI","name":"Liechtenstein","domains":9,"share":3.007e-5},{"id":"LY","name":"Libya","domains":9,"share":3.007e-5},{"id":"BF","name":"Burkina Faso","domains":8,"share":2.6729e-5},{"id":"BW","name":"Botswana","domains":8,"share":2.6729e-5},{"id":"RE","name":"R\u00e9union","domains":8,"share":2.6729e-5},{"id":"SO","name":"Somalia","domains":8,"share":2.6729e-5},{"id":"SV","name":"El Salvador","domains":8,"share":2.6729e-5},{"id":"BZ","name":"Belize","domains":7,"share":2.3388e-5},{"id":"MD","name":"Moldova, Republic of","domains":7,"share":2.3388e-5},{"id":"NI","name":"Nicaragua","domains":7,"share":2.3388e-5},{"id":"QA","name":"Qatar","domains":7,"share":2.3388e-5},{"id":"TG","name":"Togo","domains":7,"share":2.3388e-5},{"id":"JE","name":"Jersey","domains":6,"share":2.0046e-5},{"id":"KG","name":"Kyrgyzstan","domains":6,"share":2.0046e-5},{"id":"MU","name":"Mauritius","domains":6,"share":2.0046e-5},{"id":"AG","name":"Antigua and Barbuda","domains":5,"share":1.6705e-5},{"id":"BA","name":"Bosnia and Herzegovina","domains":5,"share":1.6705e-5},{"id":"IM","name":"Isle of Man","domains":5,"share":1.6705e-5},{"id":"MQ","name":"Martinique","domains":5,"share":1.6705e-5},{"id":"MW","name":"Malawi","domains":5,"share":1.6705e-5},{"id":"TD","name":"Chad","domains":5,"share":1.6705e-5},{"id":"AS","name":"American Samoa","domains":4,"share":1.3364e-5},{"id":"BV","name":"Bouvet Island","domains":4,"share":1.3364e-5},{"id":"JM","name":"Jamaica","domains":4,"share":1.3364e-5},{"id":"PS","name":"Palestine, State of","domains":4,"share":1.3364e-5},{"id":"SD","name":"Sudan","domains":4,"share":1.3364e-5},{"id":"TM","name":"Turkmenistan","domains":4,"share":1.3364e-5},{"id":"VI","name":"Virgin Islands (U.S.)","domains":4,"share":1.3364e-5},{"id":"AD","name":"Andorra","domains":3,"share":1.0023e-5},{"id":"BH","name":"Bahrain","domains":3,"share":1.0023e-5},{"id":"BI","name":"Burundi","domains":3,"share":1.0023e-5},{"id":"DM","name":"Dominica","domains":3,"share":1.0023e-5},{"id":"ET","name":"Ethiopia","domains":3,"share":1.0023e-5},{"id":"GY","name":"Guyana","domains":3,"share":1.0023e-5},{"id":"LA","name":"Lao People's Democratic Republic","domains":3,"share":1.0023e-5},{"id":"ME","name":"Montenegro","domains":3,"share":1.0023e-5},{"id":"MO","name":"Macao","domains":3,"share":1.0023e-5},{"id":"MV","name":"Maldives","domains":3,"share":1.0023e-5},{"id":"NE","name":"Niger","domains":3,"share":1.0023e-5},{"id":"SL","name":"Sierra Leone","domains":3,"share":1.0023e-5},{"id":"TT","name":"Trinidad and Tobago","domains":3,"share":1.0023e-5},{"id":"VG","name":"Virgin Islands (British)","domains":3,"share":1.0023e-5},{"id":"WS","name":"Samoa","domains":3,"share":1.0023e-5},{"id":"BT","name":"Bhutan","domains":2,"share":6.682e-6},{"id":"CG","name":"Congo","domains":2,"share":6.682e-6},{"id":"CV","name":"Cabo Verde","domains":2,"share":6.682e-6},{"id":"CW","name":"Cura\u00e7ao","domains":2,"share":6.682e-6},{"id":"GD","name":"Grenada","domains":2,"share":6.682e-6},{"id":"GI","name":"Gibraltar","domains":2,"share":6.682e-6},{"id":"GM","name":"Gambia","domains":2,"share":6.682e-6},{"id":"GP","name":"Guadeloupe","domains":2,"share":6.682e-6},{"id":"HT","name":"Haiti","domains":2,"share":6.682e-6},{"id":"LR","name":"Liberia","domains":2,"share":6.682e-6},{"id":"ML","name":"Mali","domains":2,"share":6.682e-6},{"id":"MR","name":"Mauritania","domains":2,"share":6.682e-6},{"id":"NR","name":"Nauru","domains":2,"share":6.682e-6},{"id":"PF","name":"French Polynesia","domains":2,"share":6.682e-6},{"id":"RW","name":"Rwanda","domains":2,"share":6.682e-6},{"id":"VC","name":"Saint Vincent and the Grenadines","domains":2,"share":6.682e-6},{"id":"AQ","name":"Antarctica","domains":1,"share":3.341e-6},{"id":"BB","name":"Barbados","domains":1,"share":3.341e-6},{"id":"BN","name":"Brunei Darussalam","domains":1,"share":3.341e-6},{"id":"CF","name":"Central African Republic","domains":1,"share":3.341e-6},{"id":"CK","name":"Cook Islands","domains":1,"share":3.341e-6},{"id":"CU","name":"Cuba","domains":1,"share":3.341e-6},{"id":"FJ","name":"Fiji","domains":1,"share":3.341e-6},{"id":"FK","name":"Falkland Islands (Malvinas)","domains":1,"share":3.341e-6},{"id":"FO","name":"Faroe Islands","domains":1,"share":3.341e-6},{"id":"GL","name":"Greenland","domains":1,"share":3.341e-6},{"id":"GN","name":"Guinea","domains":1,"share":3.341e-6},{"id":"GU","name":"Guam","domains":1,"share":3.341e-6},{"id":"IO","name":"British Indian Ocean Territory","domains":1,"share":3.341e-6},{"id":"LC","name":"Saint Lucia","domains":1,"share":3.341e-6},{"id":"LS","name":"Lesotho","domains":1,"share":3.341e-6},{"id":"MC","name":"Monaco","domains":1,"share":3.341e-6},{"id":"MG","name":"Madagascar","domains":1,"share":3.341e-6},{"id":"NC","name":"New Caledonia","domains":1,"share":3.341e-6},{"id":"PW","name":"Palau","domains":1,"share":3.341e-6},{"id":"SM","name":"San Marino","domains":1,"share":3.341e-6},{"id":"SR","name":"Suriname","domains":1,"share":3.341e-6},{"id":"ST","name":"Sao Tome and Principe","domains":1,"share":3.341e-6},{"id":"SZ","name":"Eswatini","domains":1,"share":3.341e-6},{"id":"TL","name":"Timor-Leste","domains":1,"share":3.341e-6},{"id":"UM","name":"United States Minor Outlying Islands","domains":1,"share":3.341e-6}],"total":299297}