{"top":[{"id":"US","name":"United States of America","domains":71949,"share":0.31208},{"id":"ZZ","name":"Unknown","domains":45259,"share":0.196311},{"id":"CN","name":"China","domains":22820,"share":0.098982},{"id":"IS","name":"Iceland","domains":17516,"share":0.0759758},{"id":"CA","name":"Canada","domains":10372,"share":0.0449887},{"id":"JP","name":"Japan","domains":10159,"share":0.0440648},{"id":"MY","name":"Malaysia","domains":5635,"share":0.0244419},{"id":"GB","name":"United Kingdom of Great Britain and Northern Ireland","domains":5521,"share":0.0239474},{"id":"FR","name":"France","domains":4263,"share":0.0184908},{"id":"IN","name":"India","domains":3007,"share":0.0130429},{"id":"XX","name":"Hidden","domains":2767,"share":0.0120019},{"id":"RU","name":"Russian Federation","domains":2505,"share":0.0108655},{"id":"DE","name":"Germany","domains":2349,"share":0.0101888},{"id":"BR","name":"Brazil","domains":2345,"share":0.0101715},{"id":"NL","name":"Netherlands","domains":1949,"share":0.00845381},{"id":"IT","name":"Italy","domains":1549,"share":0.0067188},{"id":"TR","name":"Turkey","domains":1390,"share":0.00602914},{"id":"UA","name":"Ukraine","domains":1275,"share":0.00553033},{"id":"ES","name":"Spain","domains":1110,"share":0.00481464},{"id":"VN","name":"Viet Nam","domains":1086,"share":0.00471054},{"id":"AU","name":"Australia","domains":966,"share":0.00419004},{"id":"ZA","name":"South Africa","domains":887,"share":0.00384737},{"id":"KR","name":"Korea, Republic of","domains":811,"share":0.00351772},{"id":"PA","name":"Panama","domains":734,"share":0.00318373},{"id":"AT","name":"Austria","domains":682,"share":0.00295818},{"id":"MX","name":"Mexico","domains":667,"share":0.00289312},{"id":"ID","name":"Indonesia","domains":660,"share":0.00286276},{"id":"CZ","name":"Czechia","domains":624,"share":0.00270661},{"id":"PL","name":"Poland","domains":529,"share":0.00229454},{"id":"CH","name":"Switzerland","domains":473,"share":0.00205164},{"id":"DK","name":"Denmark","domains":460,"share":0.00199525},{"id":"NG","name":"Nigeria","domains":398,"share":0.00172633},{"id":"HU","name":"Hungary","domains":351,"share":0.00152247},{"id":"SE","name":"Sweden","domains":338,"share":0.00146608},{"id":"SK","name":"Slovakia","domains":321,"share":0.00139234},{"id":"BE","name":"Belgium","domains":308,"share":0.00133595},{"id":"HK","name":"Hong Kong","domains":264,"share":0.0011451},{"id":"FI","name":"Finland","domains":260,"share":0.00112775},{"id":"RO","name":"Romania","domains":244,"share":0.00105835},{"id":"BS","name":"Bahamas","domains":219,"share":0.000949914},{"id":"PT","name":"Portugal","domains":209,"share":0.000906539},{"id":"NZ","name":"New Zealand","domains":208,"share":0.000902202},{"id":"PK","name":"Pakistan","domains":207,"share":0.000897864},{"id":"TH","name":"Thailand","domains":193,"share":0.000837139},{"id":"IL","name":"Israel","domains":188,"share":0.000815451},{"id":"MT","name":"Malta","domains":186,"share":0.000806776},{"id":"BD","name":"Bangladesh","domains":180,"share":0.000780751},{"id":"NO","name":"Norway","domains":180,"share":0.000780751},{"id":"KE","name":"Kenya","domains":174,"share":0.000754726},{"id":"CY","name":"Cyprus","domains":172,"share":0.000746051},{"id":"KZ","name":"Kazakhstan","domains":162,"share":0.000702676},{"id":"AR","name":"Argentina","domains":161,"share":0.000698339},{"id":"BG","name":"Bulgaria","domains":144,"share":0.000624601},{"id":"EE","name":"Estonia","domains":141,"share":0.000611588},{"id":"AE","name":"United Arab Emirates","domains":138,"share":0.000598576},{"id":"PH","name":"Philippines","domains":138,"share":0.000598576},{"id":"IE","name":"Ireland","domains":132,"share":0.000572551},{"id":"SA","name":"Saudi Arabia","domains":118,"share":0.000511826},{"id":"SG","name":"Singapore","domains":114,"share":0.000494476},{"id":"TW","name":"Taiwan, Province of China","domains":108,"share":0.000468451},{"id":"CO","name":"Colombia","domains":105,"share":0.000455438},{"id":"IR","name":"Iran (Islamic Republic of)","domains":95,"share":0.000412063},{"id":"MA","name":"Morocco","domains":92,"share":0.00039905},{"id":"EG","name":"Egypt","domains":89,"share":0.000386038},{"id":"PE","name":"Peru","domains":84,"share":0.00036435},{"id":"KY","name":"Cayman Islands","domains":81,"share":0.000351338},{"id":"GR","name":"Greece","domains":66,"share":0.000286275},{"id":"HR","name":"Croatia","domains":61,"share":0.000264588},{"id":"LU","name":"Luxembourg","domains":56,"share":0.0002429},{"id":"KN","name":"Saint Kitts and Nevis","domains":55,"share":0.000238563},{"id":"CL","name":"Chile","domains":54,"share":0.000234225},{"id":"DZ","name":"Algeria","domains":47,"share":0.000203862},{"id":"KH","name":"Cambodia","domains":46,"share":0.000199525},{"id":"BY","name":"Belarus","domains":45,"share":0.000195187},{"id":"UZ","name":"Uzbekistan","domains":45,"share":0.000195187},{"id":"EC","name":"Ecuador","domains":43,"share":0.000186512},{"id":"RS","name":"Serbia","domains":42,"share":0.000182175},{"id":"AM","name":"Armenia","domains":39,"share":0.000169162},{"id":"GH","name":"Ghana","domains":38,"share":0.000164825},{"id":"CM","name":"Cameroon","domains":37,"share":0.000160487},{"id":"SI","name":"Slovenia","domains":35,"share":0.000151812},{"id":"TN","name":"Tunisia","domains":35,"share":0.000151812},{"id":"TJ","name":"Tajikistan","domains":32,"share":0.0001388},{"id":"LT","name":"Lithuania","domains":30,"share":0.000130125},{"id":"VE","name":"Venezuela (Bolivarian Republic of)","domains":29,"share":0.000125787},{"id":"BO","name":"Bolivia (Plurinational State of)","domains":28,"share":0.00012145},{"id":"LK","name":"Sri Lanka","domains":27,"share":0.000117112},{"id":"JO","name":"Jordan","domains":26,"share":0.000112775},{"id":"GG","name":"Guernsey","domains":24,"share":0.0001041},{"id":"LV","name":"Latvia","domains":24,"share":0.0001041},{"id":"CR","name":"Costa Rica","domains":22,"share":9.5425e-5},{"id":"DO","name":"Dominican Republic","domains":22,"share":9.5425e-5},{"id":"SN","name":"Senegal","domains":22,"share":9.5425e-5},{"id":"CD","name":"Congo, Democratic Republic of the","domains":20,"share":8.675e-5},{"id":"BJ","name":"Benin","domains":19,"share":8.2412e-5},{"id":"CI","name":"C\u00f4te d'Ivoire","domains":19,"share":8.2412e-5},{"id":"MC","name":"Monaco","domains":19,"share":8.2412e-5},{"id":"AG","name":"Antigua and Barbuda","domains":18,"share":7.8075e-5},{"id":"NP","name":"Nepal","domains":18,"share":7.8075e-5},{"id":"ZW","name":"Zimbabwe","domains":18,"share":7.8075e-5},{"id":"GE","name":"Georgia","domains":17,"share":7.3737e-5},{"id":"MN","name":"Mongolia","domains":17,"share":7.3737e-5},{"id":"UG","name":"Uganda","domains":17,"share":7.3737e-5},{"id":"AD","name":"Andorra","domains":15,"share":6.5062e-5},{"id":"MD","name":"Moldova, Republic of","domains":15,"share":6.5062e-5},{"id":"GT","name":"Guatemala","domains":14,"share":6.0725e-5},{"id":"IQ","name":"Iraq","domains":14,"share":6.0725e-5},{"id":"AL","name":"Albania","domains":13,"share":5.6387e-5},{"id":"PS","name":"Palestine, State of","domains":13,"share":5.6387e-5},{"id":"RE","name":"R\u00e9union","domains":13,"share":5.6387e-5},{"id":"AZ","name":"Azerbaijan","domains":12,"share":5.205e-5},{"id":"BW","name":"Botswana","domains":12,"share":5.205e-5},{"id":"KG","name":"Kyrgyzstan","domains":12,"share":5.205e-5},{"id":"OM","name":"Oman","domains":12,"share":5.205e-5},{"id":"SO","name":"Somalia","domains":12,"share":5.205e-5},{"id":"GP","name":"Guadeloupe","domains":11,"share":4.7712e-5},{"id":"NA","name":"Namibia","domains":11,"share":4.7712e-5},{"id":"PR","name":"Puerto Rico","domains":11,"share":4.7712e-5},{"id":"LY","name":"Libya","domains":10,"share":4.3375e-5},{"id":"SV","name":"El Salvador","domains":10,"share":4.3375e-5},{"id":"JM","name":"Jamaica","domains":9,"share":3.9037e-5},{"id":"SC","name":"Seychelles","domains":9,"share":3.9037e-5},{"id":"CW","name":"Cura\u00e7ao","domains":8,"share":3.47e-5},{"id":"GA","name":"Gabon","domains":8,"share":3.47e-5},{"id":"GF","name":"French Guiana","domains":8,"share":3.47e-5},{"id":"KW","name":"Kuwait","domains":8,"share":3.47e-5},{"id":"LB","name":"Lebanon","domains":8,"share":3.47e-5},{"id":"TZ","name":"Tanzania, United Republic of","domains":8,"share":3.47e-5},{"id":"AO","name":"Angola","domains":7,"share":3.0362e-5},{"id":"BH","name":"Bahrain","domains":7,"share":3.0362e-5},{"id":"BZ","name":"Belize","domains":7,"share":3.0362e-5},{"id":"MG","name":"Madagascar","domains":7,"share":3.0362e-5},{"id":"MM","name":"Myanmar","domains":7,"share":3.0362e-5},{"id":"NI","name":"Nicaragua","domains":7,"share":3.0362e-5},{"id":"QA","name":"Qatar","domains":7,"share":3.0362e-5},{"id":"TC","name":"Turks and Caicos Islands","domains":7,"share":3.0362e-5},{"id":"YE","name":"Yemen","domains":7,"share":3.0362e-5},{"id":"AF","name":"Afghanistan","domains":6,"share":2.6025e-5},{"id":"LI","name":"Liechtenstein","domains":6,"share":2.6025e-5},{"id":"MU","name":"Mauritius","domains":6,"share":2.6025e-5},{"id":"MW","name":"Malawi","domains":6,"share":2.6025e-5},{"id":"PY","name":"Paraguay","domains":6,"share":2.6025e-5},{"id":"RW","name":"Rwanda","domains":6,"share":2.6025e-5},{"id":"TM","name":"Turkmenistan","domains":6,"share":2.6025e-5},{"id":"UY","name":"Uruguay","domains":6,"share":2.6025e-5},{"id":"BA","name":"Bosnia and Herzegovina","domains":5,"share":2.1687e-5},{"id":"GM","name":"Gambia","domains":5,"share":2.1687e-5},{"id":"HN","name":"Honduras","domains":5,"share":2.1687e-5},{"id":"ML","name":"Mali","domains":5,"share":2.1687e-5},{"id":"MZ","name":"Mozambique","domains":5,"share":2.1687e-5},{"id":"SZ","name":"Eswatini","domains":5,"share":2.1687e-5},{"id":"TG","name":"Togo","domains":5,"share":2.1687e-5},{"id":"VA","name":"Holy See","domains":5,"share":2.1687e-5},{"id":"BV","name":"Bouvet Island","domains":4,"share":1.735e-5},{"id":"MO","name":"Macao","domains":4,"share":1.735e-5},{"id":"NE","name":"Niger","domains":4,"share":1.735e-5},{"id":"PF","name":"French Polynesia","domains":4,"share":1.735e-5},{"id":"SR","name":"Suriname","domains":4,"share":1.735e-5},{"id":"ZM","name":"Zambia","domains":4,"share":1.735e-5},{"id":"BF","name":"Burkina Faso","domains":3,"share":1.3012e-5},{"id":"HT","name":"Haiti","domains":3,"share":1.3012e-5},{"id":"MQ","name":"Martinique","domains":3,"share":1.3012e-5},{"id":"VG","name":"Virgin Islands (British)","domains":3,"share":1.3012e-5},{"id":"AS","name":"American Samoa","domains":2,"share":8.675e-6},{"id":"BI","name":"Burundi","domains":2,"share":8.675e-6},{"id":"ET","name":"Ethiopia","domains":2,"share":8.675e-6},{"id":"FO","name":"Faroe Islands","domains":2,"share":8.675e-6},{"id":"GI","name":"Gibraltar","domains":2,"share":8.675e-6},{"id":"GL","name":"Greenland","domains":2,"share":8.675e-6},{"id":"GN","name":"Guinea","domains":2,"share":8.675e-6},{"id":"GU","name":"Guam","domains":2,"share":8.675e-6},{"id":"JE","name":"Jersey","domains":2,"share":8.675e-6},{"id":"KM","name":"Comoros","domains":2,"share":8.675e-6},{"id":"SD","name":"Sudan","domains":2,"share":8.675e-6},{"id":"TD","name":"Chad","domains":2,"share":8.675e-6},{"id":"TT","name":"Trinidad and Tobago","domains":2,"share":8.675e-6},{"id":"VC","name":"Saint Vincent and the Grenadines","domains":2,"share":8.675e-6},{"id":"VI","name":"Virgin Islands (U.S.)","domains":2,"share":8.675e-6},{"id":"AI","name":"Anguilla","domains":1,"share":4.337e-6},{"id":"AQ","name":"Antarctica","domains":1,"share":4.337e-6},{"id":"AW","name":"Aruba","domains":1,"share":4.337e-6},{"id":"BB","name":"Barbados","domains":1,"share":4.337e-6},{"id":"BM","name":"Bermuda","domains":1,"share":4.337e-6},{"id":"BN","name":"Brunei Darussalam","domains":1,"share":4.337e-6},{"id":"BQ","name":"Bonaire, Sint Eustatius and Saba","domains":1,"share":4.337e-6},{"id":"BT","name":"Bhutan","domains":1,"share":4.337e-6},{"id":"CG","name":"Congo","domains":1,"share":4.337e-6},{"id":"CV","name":"Cabo Verde","domains":1,"share":4.337e-6},{"id":"DM","name":"Dominica","domains":1,"share":4.337e-6},{"id":"FJ","name":"Fiji","domains":1,"share":4.337e-6},{"id":"GD","name":"Grenada","domains":1,"share":4.337e-6},{"id":"GQ","name":"Equatorial Guinea","domains":1,"share":4.337e-6},{"id":"LC","name":"Saint Lucia","domains":1,"share":4.337e-6},{"id":"LR","name":"Liberia","domains":1,"share":4.337e-6},{"id":"ME","name":"Montenegro","domains":1,"share":4.337e-6},{"id":"MV","name":"Maldives","domains":1,"share":4.337e-6},{"id":"SL","name":"Sierra Leone","domains":1,"share":4.337e-6},{"id":"SM","name":"San Marino","domains":1,"share":4.337e-6},{"id":"YT","name":"Mayotte","domains":1,"share":4.337e-6}],"total":230547}