{"top":[{"id":"US","name":"United States of America","domains":40399,"share":0.343968},{"id":"ZZ","name":"Unknown","domains":35039,"share":0.298331},{"id":"CA","name":"Canada","domains":6788,"share":0.0577948},{"id":"CN","name":"China","domains":5762,"share":0.0490592},{"id":"IS","name":"Iceland","domains":5735,"share":0.0488293},{"id":"XX","name":"Hidden","domains":2019,"share":0.0171903},{"id":"JP","name":"Japan","domains":1849,"share":0.0157429},{"id":"GB","name":"United Kingdom of Great Britain and Northern Ireland","domains":1676,"share":0.0142699},{"id":"FR","name":"France","domains":1587,"share":0.0135121},{"id":"IT","name":"Italy","domains":1347,"share":0.0114687},{"id":"IN","name":"India","domains":1267,"share":0.0107876},{"id":"VN","name":"Viet Nam","domains":1207,"share":0.0102767},{"id":"DE","name":"Germany","domains":1192,"share":0.010149},{"id":"BR","name":"Brazil","domains":1140,"share":0.00970626},{"id":"ES","name":"Spain","domains":679,"share":0.00578118},{"id":"NL","name":"Netherlands","domains":667,"share":0.00567901},{"id":"ZA","name":"South Africa","domains":609,"share":0.00518519},{"id":"KR","name":"Korea, Republic of","domains":477,"share":0.0040613},{"id":"AU","name":"Australia","domains":474,"share":0.00403576},{"id":"CZ","name":"Czechia","domains":464,"share":0.00395062},{"id":"MX","name":"Mexico","domains":425,"share":0.00361856},{"id":"PH","name":"Philippines","domains":336,"share":0.00286079},{"id":"MY","name":"Malaysia","domains":320,"share":0.00272456},{"id":"TR","name":"Turkey","domains":299,"share":0.00254576},{"id":"RU","name":"Russian Federation","domains":289,"share":0.00246062},{"id":"CH","name":"Switzerland","domains":287,"share":0.00244359},{"id":"SE","name":"Sweden","domains":275,"share":0.00234142},{"id":"ID","name":"Indonesia","domains":221,"share":0.00188165},{"id":"AT","name":"Austria","domains":218,"share":0.00185611},{"id":"AE","name":"United Arab Emirates","domains":216,"share":0.00183908},{"id":"CO","name":"Colombia","domains":187,"share":0.00159217},{"id":"PL","name":"Poland","domains":185,"share":0.00157514},{"id":"DK","name":"Denmark","domains":160,"share":0.00136228},{"id":"FI","name":"Finland","domains":157,"share":0.00133674},{"id":"SK","name":"Slovakia","domains":154,"share":0.0013112},{"id":"UA","name":"Ukraine","domains":146,"share":0.00124308},{"id":"NG","name":"Nigeria","domains":139,"share":0.00118348},{"id":"PT","name":"Portugal","domains":139,"share":0.00118348},{"id":"IL","name":"Israel","domains":131,"share":0.00111537},{"id":"BE","name":"Belgium","domains":120,"share":0.00102171},{"id":"HK","name":"Hong Kong","domains":117,"share":0.000996168},{"id":"CY","name":"Cyprus","domains":110,"share":0.000936568},{"id":"TH","name":"Thailand","domains":107,"share":0.000911025},{"id":"EE","name":"Estonia","domains":104,"share":0.000885483},{"id":"NO","name":"Norway","domains":97,"share":0.000825883},{"id":"RO","name":"Romania","domains":95,"share":0.000808854},{"id":"NZ","name":"New Zealand","domains":91,"share":0.000774797},{"id":"IE","name":"Ireland","domains":81,"share":0.000689655},{"id":"BS","name":"Bahamas","domains":80,"share":0.00068114},{"id":"GR","name":"Greece","domains":79,"share":0.000672626},{"id":"PA","name":"Panama","domains":72,"share":0.000613026},{"id":"KZ","name":"Kazakhstan","domains":68,"share":0.000578969},{"id":"PE","name":"Peru","domains":65,"share":0.000553426},{"id":"TW","name":"Taiwan, Province of China","domains":64,"share":0.000544912},{"id":"HR","name":"Croatia","domains":63,"share":0.000536398},{"id":"BD","name":"Bangladesh","domains":62,"share":0.000527884},{"id":"PK","name":"Pakistan","domains":62,"share":0.000527884},{"id":"BG","name":"Bulgaria","domains":61,"share":0.000519369},{"id":"SG","name":"Singapore","domains":59,"share":0.000502341},{"id":"KE","name":"Kenya","domains":57,"share":0.000485312},{"id":"IR","name":"Iran (Islamic Republic of)","domains":55,"share":0.000468284},{"id":"HU","name":"Hungary","domains":53,"share":0.000451255},{"id":"AR","name":"Argentina","domains":49,"share":0.000417198},{"id":"SA","name":"Saudi Arabia","domains":44,"share":0.000374627},{"id":"CL","name":"Chile","domains":43,"share":0.000366113},{"id":"EG","name":"Egypt","domains":35,"share":0.000297999},{"id":"GG","name":"Guernsey","domains":35,"share":0.000297999},{"id":"AF","name":"Afghanistan","domains":31,"share":0.000263942},{"id":"RS","name":"Serbia","domains":31,"share":0.000263942},{"id":"UZ","name":"Uzbekistan","domains":31,"share":0.000263942},{"id":"AM","name":"Armenia","domains":26,"share":0.00022137},{"id":"MA","name":"Morocco","domains":26,"share":0.00022137},{"id":"TN","name":"Tunisia","domains":25,"share":0.000212856},{"id":"KY","name":"Cayman Islands","domains":23,"share":0.000195828},{"id":"LU","name":"Luxembourg","domains":22,"share":0.000187313},{"id":"GH","name":"Ghana","domains":17,"share":0.000144742},{"id":"LK","name":"Sri Lanka","domains":17,"share":0.000144742},{"id":"LT","name":"Lithuania","domains":17,"share":0.000144742},{"id":"BO","name":"Bolivia (Plurinational State of)","domains":14,"share":0.000119199},{"id":"CR","name":"Costa Rica","domains":14,"share":0.000119199},{"id":"SI","name":"Slovenia","domains":14,"share":0.000119199},{"id":"CI","name":"C\u00f4te d'Ivoire","domains":13,"share":0.000110685},{"id":"MT","name":"Malta","domains":13,"share":0.000110685},{"id":"NP","name":"Nepal","domains":13,"share":0.000110685},{"id":"BH","name":"Bahrain","domains":12,"share":0.000102171},{"id":"EC","name":"Ecuador","domains":12,"share":0.000102171},{"id":"KN","name":"Saint Kitts and Nevis","domains":12,"share":0.000102171},{"id":"LV","name":"Latvia","domains":12,"share":0.000102171},{"id":"DO","name":"Dominican Republic","domains":11,"share":9.3656e-5},{"id":"GT","name":"Guatemala","domains":11,"share":9.3656e-5},{"id":"JO","name":"Jordan","domains":11,"share":9.3656e-5},{"id":"LB","name":"Lebanon","domains":11,"share":9.3656e-5},{"id":"BV","name":"Bouvet Island","domains":10,"share":8.5142e-5},{"id":"BW","name":"Botswana","domains":10,"share":8.5142e-5},{"id":"OM","name":"Oman","domains":10,"share":8.5142e-5},{"id":"VE","name":"Venezuela (Bolivarian Republic of)","domains":10,"share":8.5142e-5},{"id":"HN","name":"Honduras","domains":9,"share":7.6628e-5},{"id":"IQ","name":"Iraq","domains":9,"share":7.6628e-5},{"id":"CD","name":"Congo, Democratic Republic of the","domains":8,"share":6.8114e-5},{"id":"DZ","name":"Algeria","domains":8,"share":6.8114e-5},{"id":"LY","name":"Libya","domains":8,"share":6.8114e-5},{"id":"MM","name":"Myanmar","domains":8,"share":6.8114e-5},{"id":"MN","name":"Mongolia","domains":8,"share":6.8114e-5},{"id":"BY","name":"Belarus","domains":7,"share":5.9599e-5},{"id":"CM","name":"Cameroon","domains":7,"share":5.9599e-5},{"id":"MZ","name":"Mozambique","domains":7,"share":5.9599e-5},{"id":"PR","name":"Puerto Rico","domains":7,"share":5.9599e-5},{"id":"KM","name":"Comoros","domains":6,"share":5.1085e-5},{"id":"KW","name":"Kuwait","domains":6,"share":5.1085e-5},{"id":"QA","name":"Qatar","domains":6,"share":5.1085e-5},{"id":"UG","name":"Uganda","domains":6,"share":5.1085e-5},{"id":"UY","name":"Uruguay","domains":6,"share":5.1085e-5},{"id":"VG","name":"Virgin Islands (British)","domains":6,"share":5.1085e-5},{"id":"AO","name":"Angola","domains":5,"share":4.2571e-5},{"id":"AZ","name":"Azerbaijan","domains":5,"share":4.2571e-5},{"id":"BA","name":"Bosnia and Herzegovina","domains":5,"share":4.2571e-5},{"id":"KH","name":"Cambodia","domains":5,"share":4.2571e-5},{"id":"NA","name":"Namibia","domains":5,"share":4.2571e-5},{"id":"NI","name":"Nicaragua","domains":5,"share":4.2571e-5},{"id":"PY","name":"Paraguay","domains":5,"share":4.2571e-5},{"id":"RE","name":"R\u00e9union","domains":5,"share":4.2571e-5},{"id":"SN","name":"Senegal","domains":5,"share":4.2571e-5},{"id":"ZM","name":"Zambia","domains":5,"share":4.2571e-5},{"id":"BJ","name":"Benin","domains":4,"share":3.4057e-5},{"id":"PS","name":"Palestine, State of","domains":4,"share":3.4057e-5},{"id":"SV","name":"El Salvador","domains":4,"share":3.4057e-5},{"id":"YE","name":"Yemen","domains":4,"share":3.4057e-5},{"id":"ZW","name":"Zimbabwe","domains":4,"share":3.4057e-5},{"id":"AL","name":"Albania","domains":3,"share":2.5542e-5},{"id":"CG","name":"Congo","domains":3,"share":2.5542e-5},{"id":"FJ","name":"Fiji","domains":3,"share":2.5542e-5},{"id":"HT","name":"Haiti","domains":3,"share":2.5542e-5},{"id":"JE","name":"Jersey","domains":3,"share":2.5542e-5},{"id":"KG","name":"Kyrgyzstan","domains":3,"share":2.5542e-5},{"id":"ML","name":"Mali","domains":3,"share":2.5542e-5},{"id":"MQ","name":"Martinique","domains":3,"share":2.5542e-5},{"id":"SC","name":"Seychelles","domains":3,"share":2.5542e-5},{"id":"VI","name":"Virgin Islands (U.S.)","domains":3,"share":2.5542e-5},{"id":"BF","name":"Burkina Faso","domains":2,"share":1.7028e-5},{"id":"CW","name":"Cura\u00e7ao","domains":2,"share":1.7028e-5},{"id":"GE","name":"Georgia","domains":2,"share":1.7028e-5},{"id":"GI","name":"Gibraltar","domains":2,"share":1.7028e-5},{"id":"GL","name":"Greenland","domains":2,"share":1.7028e-5},{"id":"GM","name":"Gambia","domains":2,"share":1.7028e-5},{"id":"GP","name":"Guadeloupe","domains":2,"share":1.7028e-5},{"id":"MK","name":"North Macedonia","domains":2,"share":1.7028e-5},{"id":"MO","name":"Macao","domains":2,"share":1.7028e-5},{"id":"MU","name":"Mauritius","domains":2,"share":1.7028e-5},{"id":"RW","name":"Rwanda","domains":2,"share":1.7028e-5},{"id":"SO","name":"Somalia","domains":2,"share":1.7028e-5},{"id":"TD","name":"Chad","domains":2,"share":1.7028e-5},{"id":"TG","name":"Togo","domains":2,"share":1.7028e-5},{"id":"TZ","name":"Tanzania, United Republic of","domains":2,"share":1.7028e-5},{"id":"AD","name":"Andorra","domains":1,"share":8.514e-6},{"id":"AG","name":"Antigua and Barbuda","domains":1,"share":8.514e-6},{"id":"AI","name":"Anguilla","domains":1,"share":8.514e-6},{"id":"AQ","name":"Antarctica","domains":1,"share":8.514e-6},{"id":"AS","name":"American Samoa","domains":1,"share":8.514e-6},{"id":"BB","name":"Barbados","domains":1,"share":8.514e-6},{"id":"BI","name":"Burundi","domains":1,"share":8.514e-6},{"id":"BZ","name":"Belize","domains":1,"share":8.514e-6},{"id":"CV","name":"Cabo Verde","domains":1,"share":8.514e-6},{"id":"DJ","name":"Djibouti","domains":1,"share":8.514e-6},{"id":"ET","name":"Ethiopia","domains":1,"share":8.514e-6},{"id":"FO","name":"Faroe Islands","domains":1,"share":8.514e-6},{"id":"GA","name":"Gabon","domains":1,"share":8.514e-6},{"id":"GN","name":"Guinea","domains":1,"share":8.514e-6},{"id":"GY","name":"Guyana","domains":1,"share":8.514e-6},{"id":"JM","name":"Jamaica","domains":1,"share":8.514e-6},{"id":"LC","name":"Saint Lucia","domains":1,"share":8.514e-6},{"id":"LI","name":"Liechtenstein","domains":1,"share":8.514e-6},{"id":"MC","name":"Monaco","domains":1,"share":8.514e-6},{"id":"MD","name":"Moldova, Republic of","domains":1,"share":8.514e-6},{"id":"MV","name":"Maldives","domains":1,"share":8.514e-6},{"id":"MW","name":"Malawi","domains":1,"share":8.514e-6},{"id":"NC","name":"New Caledonia","domains":1,"share":8.514e-6},{"id":"NE","name":"Niger","domains":1,"share":8.514e-6},{"id":"SM","name":"San Marino","domains":1,"share":8.514e-6},{"id":"ST","name":"Sao Tome and Principe","domains":1,"share":8.514e-6},{"id":"SY","name":"Syrian Arab Republic","domains":1,"share":8.514e-6},{"id":"TC","name":"Turks and Caicos Islands","domains":1,"share":8.514e-6},{"id":"TJ","name":"Tajikistan","domains":1,"share":8.514e-6},{"id":"UM","name":"United States Minor Outlying Islands","domains":1,"share":8.514e-6}],"total":117450}