{"top":[{"id":"ZZ","name":"Unknown","domains":160602,"share":0.456972},{"id":"US","name":"United States of America","domains":79606,"share":0.226509},{"id":"CN","name":"China","domains":22478,"share":0.0639582},{"id":"IS","name":"Iceland","domains":18687,"share":0.0531714},{"id":"CA","name":"Canada","domains":13448,"share":0.0382646},{"id":"NL","name":"Netherlands","domains":4944,"share":0.0140675},{"id":"XX","name":"Hidden","domains":4419,"share":0.0125737},{"id":"JP","name":"Japan","domains":4341,"share":0.0123518},{"id":"GB","name":"United Kingdom of Great Britain and Northern Ireland","domains":3739,"share":0.0106388},{"id":"FR","name":"France","domains":3500,"share":0.0099588},{"id":"IN","name":"India","domains":2890,"share":0.00822312},{"id":"BR","name":"Brazil","domains":2670,"share":0.00759714},{"id":"MY","name":"Malaysia","domains":2288,"share":0.00651021},{"id":"DE","name":"Germany","domains":2144,"share":0.00610047},{"id":"IT","name":"Italy","domains":2054,"share":0.00584439},{"id":"RU","name":"Russian Federation","domains":1783,"share":0.0050733},{"id":"ES","name":"Spain","domains":1339,"share":0.00380995},{"id":"TR","name":"Turkey","domains":1268,"share":0.00360793},{"id":"VN","name":"Viet Nam","domains":1082,"share":0.00307869},{"id":"PA","name":"Panama","domains":1033,"share":0.00293927},{"id":"AU","name":"Australia","domains":1019,"share":0.00289943},{"id":"KR","name":"Korea, Republic of","domains":1007,"share":0.00286529},{"id":"ID","name":"Indonesia","domains":930,"share":0.0026462},{"id":"SG","name":"Singapore","domains":921,"share":0.00262059},{"id":"MX","name":"Mexico","domains":697,"share":0.00198322},{"id":"AT","name":"Austria","domains":585,"share":0.00166454},{"id":"CZ","name":"Czechia","domains":568,"share":0.00161617},{"id":"PL","name":"Poland","domains":482,"share":0.00137147},{"id":"ZA","name":"South Africa","domains":435,"share":0.00123774},{"id":"NG","name":"Nigeria","domains":423,"share":0.00120359},{"id":"UA","name":"Ukraine","domains":421,"share":0.0011979},{"id":"HU","name":"Hungary","domains":405,"share":0.00115238},{"id":"DK","name":"Denmark","domains":398,"share":0.00113246},{"id":"CH","name":"Switzerland","domains":371,"share":0.00105563},{"id":"HK","name":"Hong Kong","domains":356,"share":0.00101295},{"id":"SE","name":"Sweden","domains":333,"share":0.000947508},{"id":"CO","name":"Colombia","domains":317,"share":0.000901982},{"id":"PH","name":"Philippines","domains":285,"share":0.00081093},{"id":"AR","name":"Argentina","domains":268,"share":0.000762559},{"id":"IL","name":"Israel","domains":260,"share":0.000739796},{"id":"PT","name":"Portugal","domains":254,"share":0.000722724},{"id":"RO","name":"Romania","domains":252,"share":0.000717033},{"id":"BE","name":"Belgium","domains":241,"share":0.000685734},{"id":"BS","name":"Bahamas","domains":241,"share":0.000685734},{"id":"GA","name":"Gabon","domains":241,"share":0.000685734},{"id":"SK","name":"Slovakia","domains":207,"share":0.000588991},{"id":"FI","name":"Finland","domains":201,"share":0.000571919},{"id":"KE","name":"Kenya","domains":201,"share":0.000571919},{"id":"NO","name":"Norway","domains":192,"share":0.000546311},{"id":"BD","name":"Bangladesh","domains":189,"share":0.000537775},{"id":"BG","name":"Bulgaria","domains":185,"share":0.000526393},{"id":"PK","name":"Pakistan","domains":182,"share":0.000517857},{"id":"AE","name":"United Arab Emirates","domains":181,"share":0.000515012},{"id":"TH","name":"Thailand","domains":169,"share":0.000480867},{"id":"NZ","name":"New Zealand","domains":168,"share":0.000478022},{"id":"KZ","name":"Kazakhstan","domains":160,"share":0.000455259},{"id":"KN","name":"Saint Kitts and Nevis","domains":133,"share":0.000378434},{"id":"GR","name":"Greece","domains":128,"share":0.000364207},{"id":"IE","name":"Ireland","domains":123,"share":0.00034998},{"id":"PE","name":"Peru","domains":118,"share":0.000335753},{"id":"SA","name":"Saudi Arabia","domains":115,"share":0.000327217},{"id":"EE","name":"Estonia","domains":112,"share":0.000318681},{"id":"KY","name":"Cayman Islands","domains":106,"share":0.000301609},{"id":"MA","name":"Morocco","domains":101,"share":0.000287382},{"id":"IR","name":"Iran (Islamic Republic of)","domains":100,"share":0.000284537},{"id":"EG","name":"Egypt","domains":88,"share":0.000250392},{"id":"CY","name":"Cyprus","domains":87,"share":0.000247547},{"id":"AM","name":"Armenia","domains":84,"share":0.000239011},{"id":"HR","name":"Croatia","domains":71,"share":0.000202021},{"id":"RS","name":"Serbia","domains":63,"share":0.000179258},{"id":"UZ","name":"Uzbekistan","domains":61,"share":0.000173567},{"id":"TW","name":"Taiwan, Province of China","domains":57,"share":0.000162186},{"id":"CL","name":"Chile","domains":55,"share":0.000156495},{"id":"DZ","name":"Algeria","domains":54,"share":0.00015365},{"id":"TJ","name":"Tajikistan","domains":53,"share":0.000150804},{"id":"BY","name":"Belarus","domains":52,"share":0.000147959},{"id":"GH","name":"Ghana","domains":52,"share":0.000147959},{"id":"MO","name":"Macao","domains":51,"share":0.000145113},{"id":"EC","name":"Ecuador","domains":50,"share":0.000142268},{"id":"LU","name":"Luxembourg","domains":50,"share":0.000142268},{"id":"CI","name":"C\u00f4te d'Ivoire","domains":43,"share":0.00012235},{"id":"DO","name":"Dominican Republic","domains":42,"share":0.000119505},{"id":"JO","name":"Jordan","domains":41,"share":0.00011666},{"id":"TN","name":"Tunisia","domains":41,"share":0.00011666},{"id":"MT","name":"Malta","domains":39,"share":0.000110969},{"id":"PY","name":"Paraguay","domains":38,"share":0.000108124},{"id":"LT","name":"Lithuania","domains":37,"share":0.000105278},{"id":"BJ","name":"Benin","domains":33,"share":9.3897e-5},{"id":"CR","name":"Costa Rica","domains":32,"share":9.1051e-5},{"id":"GE","name":"Georgia","domains":32,"share":9.1051e-5},{"id":"NP","name":"Nepal","domains":32,"share":9.1051e-5},{"id":"VE","name":"Venezuela (Bolivarian Republic of)","domains":32,"share":9.1051e-5},{"id":"SN","name":"Senegal","domains":31,"share":8.8206e-5},{"id":"AF","name":"Afghanistan","domains":30,"share":8.5361e-5},{"id":"CM","name":"Cameroon","domains":29,"share":8.2515e-5},{"id":"LV","name":"Latvia","domains":28,"share":7.967e-5},{"id":"SI","name":"Slovenia","domains":27,"share":7.6825e-5},{"id":"LK","name":"Sri Lanka","domains":25,"share":7.1134e-5},{"id":"TC","name":"Turks and Caicos Islands","domains":25,"share":7.1134e-5},{"id":"PR","name":"Puerto Rico","domains":24,"share":6.8288e-5},{"id":"ZW","name":"Zimbabwe","domains":24,"share":6.8288e-5},{"id":"KH","name":"Cambodia","domains":22,"share":6.2598e-5},{"id":"BO","name":"Bolivia (Plurinational State of)","domains":21,"share":5.9752e-5},{"id":"GG","name":"Guernsey","domains":19,"share":5.4062e-5},{"id":"GT","name":"Guatemala","domains":19,"share":5.4062e-5},{"id":"CD","name":"Congo, Democratic Republic of the","domains":17,"share":4.8371e-5},{"id":"OM","name":"Oman","domains":17,"share":4.8371e-5},{"id":"SV","name":"El Salvador","domains":17,"share":4.8371e-5},{"id":"AD","name":"Andorra","domains":16,"share":4.5525e-5},{"id":"BZ","name":"Belize","domains":16,"share":4.5525e-5},{"id":"UY","name":"Uruguay","domains":16,"share":4.5525e-5},{"id":"IQ","name":"Iraq","domains":15,"share":4.268e-5},{"id":"KG","name":"Kyrgyzstan","domains":15,"share":4.268e-5},{"id":"LY","name":"Libya","domains":15,"share":4.268e-5},{"id":"RE","name":"R\u00e9union","domains":15,"share":4.268e-5},{"id":"AG","name":"Antigua and Barbuda","domains":14,"share":3.9835e-5},{"id":"AZ","name":"Azerbaijan","domains":14,"share":3.9835e-5},{"id":"AL","name":"Albania","domains":13,"share":3.6989e-5},{"id":"BF","name":"Burkina Faso","domains":13,"share":3.6989e-5},{"id":"HN","name":"Honduras","domains":13,"share":3.6989e-5},{"id":"KW","name":"Kuwait","domains":13,"share":3.6989e-5},{"id":"MD","name":"Moldova, Republic of","domains":13,"share":3.6989e-5},{"id":"MM","name":"Myanmar","domains":13,"share":3.6989e-5},{"id":"UG","name":"Uganda","domains":13,"share":3.6989e-5},{"id":"AW","name":"Aruba","domains":12,"share":3.4144e-5},{"id":"TZ","name":"Tanzania, United Republic of","domains":12,"share":3.4144e-5},{"id":"LB","name":"Lebanon","domains":11,"share":3.1299e-5},{"id":"MZ","name":"Mozambique","domains":11,"share":3.1299e-5},{"id":"TT","name":"Trinidad and Tobago","domains":11,"share":3.1299e-5},{"id":"BA","name":"Bosnia and Herzegovina","domains":10,"share":2.8453e-5},{"id":"CK","name":"Cook Islands","domains":10,"share":2.8453e-5},{"id":"GN","name":"Guinea","domains":10,"share":2.8453e-5},{"id":"NA","name":"Namibia","domains":10,"share":2.8453e-5},{"id":"BB","name":"Barbados","domains":9,"share":2.5608e-5},{"id":"QA","name":"Qatar","domains":9,"share":2.5608e-5},{"id":"ZM","name":"Zambia","domains":9,"share":2.5608e-5},{"id":"GY","name":"Guyana","domains":8,"share":2.2762e-5},{"id":"LI","name":"Liechtenstein","domains":8,"share":2.2762e-5},{"id":"NI","name":"Nicaragua","domains":8,"share":2.2762e-5},{"id":"GI","name":"Gibraltar","domains":7,"share":1.9917e-5},{"id":"MC","name":"Monaco","domains":7,"share":1.9917e-5},{"id":"NE","name":"Niger","domains":7,"share":1.9917e-5},{"id":"SC","name":"Seychelles","domains":7,"share":1.9917e-5},{"id":"BI","name":"Burundi","domains":6,"share":1.7072e-5},{"id":"GM","name":"Gambia","domains":6,"share":1.7072e-5},{"id":"IM","name":"Isle of Man","domains":6,"share":1.7072e-5},{"id":"JM","name":"Jamaica","domains":6,"share":1.7072e-5},{"id":"YE","name":"Yemen","domains":6,"share":1.7072e-5},{"id":"BH","name":"Bahrain","domains":5,"share":1.4226e-5},{"id":"BM","name":"Bermuda","domains":5,"share":1.4226e-5},{"id":"CG","name":"Congo","domains":5,"share":1.4226e-5},{"id":"MK","name":"North Macedonia","domains":5,"share":1.4226e-5},{"id":"MU","name":"Mauritius","domains":5,"share":1.4226e-5},{"id":"SD","name":"Sudan","domains":5,"share":1.4226e-5},{"id":"SM","name":"San Marino","domains":5,"share":1.4226e-5},{"id":"SO","name":"Somalia","domains":5,"share":1.4226e-5},{"id":"TD","name":"Chad","domains":5,"share":1.4226e-5},{"id":"TG","name":"Togo","domains":5,"share":1.4226e-5},{"id":"AO","name":"Angola","domains":4,"share":1.1381e-5},{"id":"BT","name":"Bhutan","domains":4,"share":1.1381e-5},{"id":"BW","name":"Botswana","domains":4,"share":1.1381e-5},{"id":"CW","name":"Cura\u00e7ao","domains":4,"share":1.1381e-5},{"id":"GP","name":"Guadeloupe","domains":4,"share":1.1381e-5},{"id":"GU","name":"Guam","domains":4,"share":1.1381e-5},{"id":"MG","name":"Madagascar","domains":4,"share":1.1381e-5},{"id":"ML","name":"Mali","domains":4,"share":1.1381e-5},{"id":"MN","name":"Mongolia","domains":4,"share":1.1381e-5},{"id":"MQ","name":"Martinique","domains":4,"share":1.1381e-5},{"id":"MR","name":"Mauritania","domains":4,"share":1.1381e-5},{"id":"MW","name":"Malawi","domains":4,"share":1.1381e-5},{"id":"PS","name":"Palestine, State of","domains":4,"share":1.1381e-5},{"id":"VG","name":"Virgin Islands (British)","domains":4,"share":1.1381e-5},{"id":"BV","name":"Bouvet Island","domains":3,"share":8.536e-6},{"id":"ET","name":"Ethiopia","domains":3,"share":8.536e-6},{"id":"FJ","name":"Fiji","domains":3,"share":8.536e-6},{"id":"GD","name":"Grenada","domains":3,"share":8.536e-6},{"id":"GW","name":"Guinea-Bissau","domains":3,"share":8.536e-6},{"id":"MV","name":"Maldives","domains":3,"share":8.536e-6},{"id":"RW","name":"Rwanda","domains":3,"share":8.536e-6},{"id":"SL","name":"Sierra Leone","domains":3,"share":8.536e-6},{"id":"TM","name":"Turkmenistan","domains":3,"share":8.536e-6},{"id":"VI","name":"Virgin Islands (U.S.)","domains":3,"share":8.536e-6},{"id":"AS","name":"American Samoa","domains":2,"share":5.69e-6},{"id":"BN","name":"Brunei Darussalam","domains":2,"share":5.69e-6},{"id":"GF","name":"French Guiana","domains":2,"share":5.69e-6},{"id":"GQ","name":"Equatorial Guinea","domains":2,"share":5.69e-6},{"id":"HT","name":"Haiti","domains":2,"share":5.69e-6},{"id":"KM","name":"Comoros","domains":2,"share":5.69e-6},{"id":"LR","name":"Liberia","domains":2,"share":5.69e-6},{"id":"MH","name":"Marshall Islands","domains":2,"share":5.69e-6},{"id":"PF","name":"French Polynesia","domains":2,"share":5.69e-6},{"id":"WF","name":"Wallis and Futuna","domains":2,"share":5.69e-6},{"id":"WS","name":"Samoa","domains":2,"share":5.69e-6},{"id":"YT","name":"Mayotte","domains":2,"share":5.69e-6},{"id":"AQ","name":"Antarctica","domains":1,"share":2.845e-6},{"id":"CC","name":"Cocos (Keeling) Islands","domains":1,"share":2.845e-6},{"id":"CF","name":"Central African Republic","domains":1,"share":2.845e-6},{"id":"ER","name":"Eritrea","domains":1,"share":2.845e-6},{"id":"JE","name":"Jersey","domains":1,"share":2.845e-6},{"id":"LA","name":"Lao People's Democratic Republic","domains":1,"share":2.845e-6},{"id":"LC","name":"Saint Lucia","domains":1,"share":2.845e-6},{"id":"NC","name":"New Caledonia","domains":1,"share":2.845e-6},{"id":"PG","name":"Papua New Guinea","domains":1,"share":2.845e-6},{"id":"SH","name":"Saint Helena, Ascension and Tristan da Cunha","domains":1,"share":2.845e-6},{"id":"SR","name":"Suriname","domains":1,"share":2.845e-6},{"id":"SS","name":"South Sudan","domains":1,"share":2.845e-6},{"id":"TF","name":"French Southern Territories","domains":1,"share":2.845e-6},{"id":"VU","name":"Vanuatu","domains":1,"share":2.845e-6}],"total":351448}