{"top":[{"id":"US","name":"United States of America","domains":2189,"share":0.30496},{"id":"ZZ","name":"Unknown","domains":1669,"share":0.232516},{"id":"GB","name":"United Kingdom of Great Britain and Northern Ireland","domains":294,"share":0.0409585},{"id":"DE","name":"Germany","domains":274,"share":0.0381722},{"id":"IT","name":"Italy","domains":273,"share":0.0380329},{"id":"CA","name":"Canada","domains":269,"share":0.0374756},{"id":"FR","name":"France","domains":202,"share":0.0281415},{"id":"ES","name":"Spain","domains":185,"share":0.0257732},{"id":"BR","name":"Brazil","domains":181,"share":0.0252159},{"id":"KY","name":"Cayman Islands","domains":171,"share":0.0238228},{"id":"CN","name":"China","domains":150,"share":0.0208972},{"id":"JP","name":"Japan","domains":115,"share":0.0160212},{"id":"XX","name":"Hidden","domains":109,"share":0.0151853},{"id":"CZ","name":"Czechia","domains":88,"share":0.0122597},{"id":"NL","name":"Netherlands","domains":75,"share":0.0104486},{"id":"PA","name":"Panama","domains":65,"share":0.00905545},{"id":"AU","name":"Australia","domains":64,"share":0.00891613},{"id":"AT","name":"Austria","domains":61,"share":0.00849819},{"id":"KR","name":"Korea, Republic of","domains":56,"share":0.00780162},{"id":"IN","name":"India","domains":53,"share":0.00738367},{"id":"SK","name":"Slovakia","domains":52,"share":0.00724436},{"id":"MX","name":"Mexico","domains":49,"share":0.00682641},{"id":"FI","name":"Finland","domains":40,"share":0.00557258},{"id":"ZA","name":"South Africa","domains":39,"share":0.00543327},{"id":"DK","name":"Denmark","domains":37,"share":0.00515464},{"id":"SE","name":"Sweden","domains":36,"share":0.00501532},{"id":"CH","name":"Switzerland","domains":29,"share":0.00404012},{"id":"HK","name":"Hong Kong","domains":22,"share":0.00306492},{"id":"PL","name":"Poland","domains":19,"share":0.00264698},{"id":"IL","name":"Israel","domains":18,"share":0.00250766},{"id":"BE","name":"Belgium","domains":16,"share":0.00222903},{"id":"LU","name":"Luxembourg","domains":16,"share":0.00222903},{"id":"MY","name":"Malaysia","domains":16,"share":0.00222903},{"id":"BG","name":"Bulgaria","domains":13,"share":0.00181109},{"id":"NO","name":"Norway","domains":13,"share":0.00181109},{"id":"PT","name":"Portugal","domains":13,"share":0.00181109},{"id":"TR","name":"Turkey","domains":13,"share":0.00181109},{"id":"IE","name":"Ireland","domains":11,"share":0.00153246},{"id":"RU","name":"Russian Federation","domains":11,"share":0.00153246},{"id":"BS","name":"Bahamas","domains":10,"share":0.00139314},{"id":"HR","name":"Croatia","domains":10,"share":0.00139314},{"id":"KN","name":"Saint Kitts and Nevis","domains":10,"share":0.00139314},{"id":"TW","name":"Taiwan, Province of China","domains":8,"share":0.00111452},{"id":"HU","name":"Hungary","domains":7,"share":0.000975202},{"id":"NZ","name":"New Zealand","domains":7,"share":0.000975202},{"id":"TH","name":"Thailand","domains":7,"share":0.000975202},{"id":"CO","name":"Colombia","domains":6,"share":0.000835887},{"id":"SG","name":"Singapore","domains":6,"share":0.000835887},{"id":"AR","name":"Argentina","domains":5,"share":0.000696572},{"id":"CR","name":"Costa Rica","domains":4,"share":0.000557258},{"id":"GR","name":"Greece","domains":4,"share":0.000557258},{"id":"SA","name":"Saudi Arabia","domains":4,"share":0.000557258},{"id":"VG","name":"Virgin Islands (British)","domains":4,"share":0.000557258},{"id":"VN","name":"Viet Nam","domains":4,"share":0.000557258},{"id":"EE","name":"Estonia","domains":3,"share":0.000417943},{"id":"EG","name":"Egypt","domains":3,"share":0.000417943},{"id":"IS","name":"Iceland","domains":3,"share":0.000417943},{"id":"PE","name":"Peru","domains":3,"share":0.000417943},{"id":"PH","name":"Philippines","domains":3,"share":0.000417943},{"id":"RO","name":"Romania","domains":3,"share":0.000417943},{"id":"RS","name":"Serbia","domains":3,"share":0.000417943},{"id":"AE","name":"United Arab Emirates","domains":2,"share":0.000278629},{"id":"BA","name":"Bosnia and Herzegovina","domains":2,"share":0.000278629},{"id":"BZ","name":"Belize","domains":2,"share":0.000278629},{"id":"ID","name":"Indonesia","domains":2,"share":0.000278629},{"id":"IM","name":"Isle of Man","domains":2,"share":0.000278629},{"id":"KE","name":"Kenya","domains":2,"share":0.000278629},{"id":"KW","name":"Kuwait","domains":2,"share":0.000278629},{"id":"KZ","name":"Kazakhstan","domains":2,"share":0.000278629},{"id":"MT","name":"Malta","domains":2,"share":0.000278629},{"id":"QA","name":"Qatar","domains":2,"share":0.000278629},{"id":"SI","name":"Slovenia","domains":2,"share":0.000278629},{"id":"UA","name":"Ukraine","domains":2,"share":0.000278629},{"id":"UY","name":"Uruguay","domains":2,"share":0.000278629},{"id":"VE","name":"Venezuela (Bolivarian Republic of)","domains":2,"share":0.000278629},{"id":"ZW","name":"Zimbabwe","domains":2,"share":0.000278629},{"id":"AD","name":"Andorra","domains":1,"share":0.000139314},{"id":"AF","name":"Afghanistan","domains":1,"share":0.000139314},{"id":"AM","name":"Armenia","domains":1,"share":0.000139314},{"id":"AZ","name":"Azerbaijan","domains":1,"share":0.000139314},{"id":"BJ","name":"Benin","domains":1,"share":0.000139314},{"id":"CL","name":"Chile","domains":1,"share":0.000139314},{"id":"CY","name":"Cyprus","domains":1,"share":0.000139314},{"id":"DO","name":"Dominican Republic","domains":1,"share":0.000139314},{"id":"EC","name":"Ecuador","domains":1,"share":0.000139314},{"id":"FO","name":"Faroe Islands","domains":1,"share":0.000139314},{"id":"GP","name":"Guadeloupe","domains":1,"share":0.000139314},{"id":"LB","name":"Lebanon","domains":1,"share":0.000139314},{"id":"MM","name":"Myanmar","domains":1,"share":0.000139314},{"id":"MO","name":"Macao","domains":1,"share":0.000139314},{"id":"MU","name":"Mauritius","domains":1,"share":0.000139314},{"id":"NA","name":"Namibia","domains":1,"share":0.000139314},{"id":"RE","name":"R\u00e9union","domains":1,"share":0.000139314},{"id":"SC","name":"Seychelles","domains":1,"share":0.000139314},{"id":"SM","name":"San Marino","domains":1,"share":0.000139314},{"id":"SV","name":"El Salvador","domains":1,"share":0.000139314},{"id":"SZ","name":"Eswatini","domains":1,"share":0.000139314},{"id":"TN","name":"Tunisia","domains":1,"share":0.000139314},{"id":"TT","name":"Trinidad and Tobago","domains":1,"share":0.000139314},{"id":"UG","name":"Uganda","domains":1,"share":0.000139314},{"id":"UM","name":"United States Minor Outlying Islands","domains":1,"share":0.000139314}],"total":7178}